vape4d-0.2.7.dist-info/METADATA
vape4d-0.2.7.dist-info/WHEEL
vape4d-0.2.7.dist-info/entry_points.txt
vape4d-0.2.7.dist-info/licenses/LICENCE
vape4d/__init__.py
vape4d/render.py
vape4d/utils.py
vape4d/vape4d.cpython-313-darwin.so
vape4d/viewer.py
vape4d-0.2.7.dist-info/RECORD
