Metadata-Version: 2.4
Name: vape4d
Version: 0.2.7
Requires-Dist: numpy
Requires-Dist: matplotlib
Requires-Dist: seaborn
Requires-Dist: cmasher
Requires-Dist: cffi
Requires-Dist: ipython ; extra == 'ipython'
Provides-Extra: ipython
License-File: LICENCE
Summary: Volume 4D Visualization
Keywords: 4D,volume,visualization,vape4d
Author: Simon Niedermayr
Requires-Python: >=3.8
Project-URL: homepage, https://keksboter.github.io/vape4d
Project-URL: repository, https://github.com/KeKsBoTer/vape4d
